semantica/__init__.py
semantica/cli.py
semantica/server.py
semantica/worker.py
semantica/conflicts/__init__.py
semantica/conflicts/config.py
semantica/conflicts/conflict_analyzer.py
semantica/conflicts/conflict_detector.py
semantica/conflicts/conflict_resolver.py
semantica/conflicts/investigation_guide.py
semantica/conflicts/methods.py
semantica/conflicts/registry.py
semantica/conflicts/source_tracker.py
semantica/context/__init__.py
semantica/context/agent_context.py
semantica/context/agent_memory.py
semantica/context/context_graph.py
semantica/context/context_retriever.py
semantica/context/entity_linker.py
semantica/core/__init__.py
semantica/core/config_manager.py
semantica/core/lifecycle.py
semantica/core/methods.py
semantica/core/orchestrator.py
semantica/core/plugin_registry.py
semantica/core/registry.py
semantica/deduplication/__init__.py
semantica/deduplication/cluster_builder.py
semantica/deduplication/config.py
semantica/deduplication/duplicate_detector.py
semantica/deduplication/entity_merger.py
semantica/deduplication/merge_strategy.py
semantica/deduplication/methods.py
semantica/deduplication/registry.py
semantica/deduplication/similarity_calculator.py
semantica/embeddings/__init__.py
semantica/embeddings/config.py
semantica/embeddings/embedding_generator.py
semantica/embeddings/graph_embedding_manager.py
semantica/embeddings/methods.py
semantica/embeddings/pooling_strategies.py
semantica/embeddings/provider_stores.py
semantica/embeddings/registry.py
semantica/embeddings/text_embedder.py
semantica/embeddings/vector_embedding_manager.py
semantica/evals/__init__.py
semantica/export/__init__.py
semantica/export/config.py
semantica/export/csv_exporter.py
semantica/export/graph_exporter.py
semantica/export/json_exporter.py
semantica/export/lpg_exporter.py
semantica/export/methods.py
semantica/export/owl_exporter.py
semantica/export/rdf_exporter.py
semantica/export/registry.py
semantica/export/report_generator.py
semantica/export/vector_exporter.py
semantica-0.2.2.dist-info/licenses/LICENSE
semantica-0.2.2.dist-info/METADATA
semantica-0.2.2.dist-info/WHEEL
semantica-0.2.2.dist-info/entry_points.txt
semantica-0.2.2.dist-info/top_level.txt
semantica-0.2.2.dist-info/RECORD
