Metadata-Version: 2.4
Name: semantica
Version: 0.2.2
Summary: 🧠 Semantica - An Open Source Framework for building Semantic Layers and Knowledge Engineering
Author-email: Hawksight AI <semantica-dev@users.noreply.github.com>
Maintainer-email: Hawksight AI <semantica-dev@users.noreply.github.com>
License: MIT
Keywords: semantic-layer,knowledge-graph,nlp,embeddings,entity-extraction,relationship-extraction,rdf,ontology
Classifier: Development Status :: 3 - Alpha
Classifier: Intended Audience :: Developers
Classifier: Intended Audience :: Science/Research
Classifier: License :: OSI Approved :: MIT License
Classifier: Operating System :: OS Independent
Classifier: Programming Language :: Python :: 3
Classifier: Programming Language :: Python :: 3.8
Classifier: Programming Language :: Python :: 3.9
Classifier: Programming Language :: Python :: 3.10
Classifier: Programming Language :: Python :: 3.11
Classifier: Programming Language :: Python :: 3.12
Classifier: Topic :: Scientific/Engineering :: Artificial Intelligence
Classifier: Topic :: Software Development :: Libraries :: Python Modules
Requires-Python: >=3.8
License-File: LICENSE
Requires-Dist: numpy>=1.21.0
Requires-Dist: pandas>=1.3.0
Requires-Dist: scikit-learn>=1.0.0
Requires-Dist: umap-learn>=0.5.0
Requires-Dist: spacy>=3.4.0
Requires-Dist: transformers>=4.20.0
Requires-Dist: torch>=1.12.0
Requires-Dist: sentence-transformers>=2.2.0
Requires-Dist: rdflib>=6.2.0
Requires-Dist: networkx>=2.8.0
Requires-Dist: matplotlib>=3.5.0
Requires-Dist: seaborn>=0.11.0
Requires-Dist: plotly>=5.10.0
Requires-Dist: ipywidgets>=8.0.0
Requires-Dist: requests>=2.28.0
Requires-Dist: GitPython>=3.1.30
Requires-Dist: chardet>=5.1.0
Requires-Dist: protobuf<7.0,>=5.29.1
Requires-Dist: grpcio>=1.71.2
Requires-Dist: beautifulsoup4>=4.11.0
Requires-Dist: lxml>=4.9.0
Requires-Dist: pypdf2>=2.10.0
Requires-Dist: python-docx>=0.8.11
Requires-Dist: openpyxl>=3.0.10
Requires-Dist: pillow>=9.2.0
Requires-Dist: librosa>=0.9.0
Requires-Dist: opencv-python>=4.6.0
Requires-Dist: faiss-cpu>=1.7.0
Requires-Dist: fastembed>=0.2.0
Requires-Dist: onnxruntime>=1.17.0
Requires-Dist: tokenizers>=0.15.0
Requires-Dist: pydantic>=2.0.0
Requires-Dist: click>=8.1.0
Requires-Dist: rich>=12.5.0
Requires-Dist: tqdm>=4.64.0
Requires-Dist: pyyaml>=6.0
Requires-Dist: toml>=0.10.0
Requires-Dist: python-dotenv>=0.20.0
Requires-Dist: loguru>=0.6.0
Requires-Dist: structlog>=22.1.0
Provides-Extra: llm-openai
Requires-Dist: openai>=1.0.0; extra == "llm-openai"
Provides-Extra: llm-groq
Requires-Dist: groq>=0.4.0; extra == "llm-groq"
Provides-Extra: llm-gemini
Requires-Dist: google-genai>=0.1.0; extra == "llm-gemini"
Provides-Extra: llm-anthropic
Requires-Dist: anthropic>=0.18.0; extra == "llm-anthropic"
Provides-Extra: llm-ollama
Requires-Dist: ollama>=0.1.0; extra == "llm-ollama"
Provides-Extra: llm-deepseek
Requires-Dist: deepseek>=0.1.0; extra == "llm-deepseek"
Provides-Extra: llm-litellm
Requires-Dist: litellm>=1.0.0; extra == "llm-litellm"
Provides-Extra: llm-instructor
Requires-Dist: instructor>=1.0.0; extra == "llm-instructor"
Provides-Extra: llm-all
Requires-Dist: semantica[llm-anthropic,llm-deepseek,llm-gemini,llm-groq,llm-instructor,llm-litellm,llm-ollama,llm-openai]; extra == "llm-all"
Provides-Extra: parse-docling
Requires-Dist: docling>=1.0.0; extra == "parse-docling"
Provides-Extra: models-huggingface
Requires-Dist: transformers>=4.20.0; extra == "models-huggingface"
Requires-Dist: torch>=1.12.0; extra == "models-huggingface"
Provides-Extra: graph-neo4j
Requires-Dist: neo4j>=5.0.0; extra == "graph-neo4j"
Provides-Extra: graph-falkordb
Requires-Dist: falkordb>=1.0.0; extra == "graph-falkordb"
Requires-Dist: redis>=4.3.0; extra == "graph-falkordb"
Provides-Extra: graph-amazon-neptune
Requires-Dist: boto3>=1.24.0; extra == "graph-amazon-neptune"
Requires-Dist: neo4j>=5.0.0; extra == "graph-amazon-neptune"
Provides-Extra: graph-all
Requires-Dist: semantica[graph-amazon-neptune,graph-falkordb,graph-neo4j]; extra == "graph-all"
Provides-Extra: infra
Requires-Dist: redis>=4.3.0; extra == "infra"
Requires-Dist: celery>=5.2.0; extra == "infra"
Requires-Dist: kafka-python>=2.0.0; extra == "infra"
Requires-Dist: pulsar-client>=3.0.0; extra == "infra"
Requires-Dist: pika>=1.3.0; extra == "infra"
Provides-Extra: cloud
Requires-Dist: boto3>=1.24.0; extra == "cloud"
Requires-Dist: azure-storage-blob>=12.12.0; extra == "cloud"
Requires-Dist: google-cloud-storage>=2.5.0; extra == "cloud"
Provides-Extra: monitoring
Requires-Dist: prometheus-client>=0.14.0; extra == "monitoring"
Requires-Dist: opentelemetry-api<2.0.0,>=1.30.0; extra == "monitoring"
Requires-Dist: opentelemetry-sdk<2.0.0,>=1.30.0; extra == "monitoring"
Requires-Dist: opentelemetry-semantic-conventions<0.61b0,>=0.58b0; extra == "monitoring"
Requires-Dist: opentelemetry-instrumentation<0.61b0,>=0.58b0; extra == "monitoring"
Provides-Extra: viz
Requires-Dist: pyvis>=0.3.0; extra == "viz"
Requires-Dist: graphviz>=0.20.0; extra == "viz"
Requires-Dist: d3blocks>=1.0.0; extra == "viz"
Provides-Extra: gpu
Requires-Dist: faiss-gpu>=1.7.0; extra == "gpu"
Requires-Dist: cupy>=10.0.0; extra == "gpu"
Provides-Extra: split-tiktoken
Requires-Dist: tiktoken>=0.5.0; extra == "split-tiktoken"
Provides-Extra: split-community
Requires-Dist: python-louvain>=0.16; extra == "split-community"
Provides-Extra: split-topic
Requires-Dist: bertopic>=0.15.0; extra == "split-topic"
Requires-Dist: gensim>=4.3.0; extra == "split-topic"
Provides-Extra: split-all
Requires-Dist: semantica[split-community,split-tiktoken,split-topic]; extra == "split-all"
Provides-Extra: dev
Requires-Dist: pytest>=7.1.0; extra == "dev"
Requires-Dist: pytest-cov>=3.0.0; extra == "dev"
Requires-Dist: pytest-asyncio>=0.19.0; extra == "dev"
Requires-Dist: black>=22.6.0; extra == "dev"
Requires-Dist: isort>=5.10.0; extra == "dev"
Requires-Dist: flake8>=4.0.0; extra == "dev"
Requires-Dist: mypy>=0.971; extra == "dev"
Requires-Dist: pre-commit>=2.19.0; extra == "dev"
Requires-Dist: jupyter>=1.0.0; extra == "dev"
Requires-Dist: ipykernel>=6.15.0; extra == "dev"
Provides-Extra: all
Requires-Dist: semantica[cloud,dev,gpu,graph-all,infra,llm-all,models-huggingface,monitoring,parse-docling,split-all,viz]; extra == "all"
Dynamic: license-file
